gateapp/__init__.py
gateapp/admin.py
gateapp/apps.py
gateapp/form.py
gateapp/models.py
gateapp/tests.py
gateapp/urls.py
gateapp/views.py
gateapp/migrations/__init__.py
gatewayApplication/__init__.py
gatewayApplication/asgi.py
gatewayApplication/settings.py
gatewayApplication/urls.py
gatewayApplication/wsgi.py
django_gateway_ip_requestlimt_interface-0.1.0.dist-info/LICENSE
django_gateway_ip_requestlimt_interface-0.1.0.dist-info/METADATA
django_gateway_ip_requestlimt_interface-0.1.0.dist-info/WHEEL
django_gateway_ip_requestlimt_interface-0.1.0.dist-info/top_level.txt
django_gateway_ip_requestlimt_interface-0.1.0.dist-info/RECORD
