Metadata-Version: 2.1
Name: django-gateway-ip-requestlimt-interface
Version: 0.1.0
Summary: A Django application for configuring gateway settings with a web-based interface
Home-page: https://github.com/ankit3388/BlockerGateway
Author: Ankit Kumar
Author-email: bantiyadav16095@gmail.com
Project-URL: Bug Reports, https://github.com/ankit3388/BlockerGateway/issues
Project-URL: Source, https://github.com/ankit3388/BlockerGateway
Keywords: django gateway interface web configuration
Classifier: Development Status :: 3 - Alpha
Classifier: Intended Audience :: Developers
Classifier: License :: OSI Approved :: MIT License
Classifier: Programming Language :: Python :: 3
Classifier: Programming Language :: Python :: 3.8
Classifier: Programming Language :: Python :: 3.9
Classifier: Programming Language :: Python :: 3.10
Classifier: Programming Language :: Python :: 3.11
Classifier: Programming Language :: Python :: 3.12
Classifier: Framework :: Django
Requires-Python: >=3.8
License-File: LICENSE
Requires-Dist: Django <5.0,>=3.0
Requires-Dist: gunicorn
